.gitignore
COPYING
MANIFEST.in
README.md
issues
setup.cfg
setup.py
test-requirements.txt
doc/.gitignore
doc/Makefile
doc/conf.py
doc/index.rst
gpgmime/__init__.py
gpgmime/errors.py
gpgmime/helper.py
gpgmime/main.py
gpgmime.egg-info/PKG-INFO
gpgmime.egg-info/SOURCES.txt
gpgmime.egg-info/dependency_links.txt
gpgmime.egg-info/requires.txt
gpgmime.egg-info/top_level.txt
testing/__init__.py
testing/utils.py
testing/gpghome/.gitignore
testing/gpghome/pubring.kbx
testing/gpghome/pubring.kbx~
testing/gpghome/random_seed
testing/gpghome/trustdb.gpg
testing/gpghome/openpgp-revocs.d/4EF877BDEEE0DDA6C9C3F9F51B83C7515522668B.rev
testing/gpghome/openpgp-revocs.d/77D0254C9A2E92214EC730B30462F3C1D9D2355B.rev
testing/gpghome/private-keys-v1.d/3BC0A5773F352C5C65EC4E72838409A351DFB920.key
testing/gpghome/private-keys-v1.d/5958509B158C9151A354427679B38E4BA55A250D.key
testing/gpghome/private-keys-v1.d/950FBC60D6B52B88318F84643C674B0308D28963.key
testing/gpghome/private-keys-v1.d/BC504BF61B0A8215F6D9282941D4222C883F6A0C.key
testing/gpghome/private-keys-v1.d/D887C1B8F515EF08150D2E1A741D8D976773773F.key
testing/gpghome/private-keys-v1.d/E974492971ADEEE2824AEE7C02AC152E8EFBA2FF.key
testing/gpghome/private-keys-v1.d/EE2AB9DBF20F8F8EDC6E89E57A26280497A11E5F.key
testing/tests/helper.py
testing/tests/main.py