Metadata-Version: 1.1
Name: gpgmime
Version: 0.1
Summary: Library for manipulating PGP-Mime email.
Home-page: https://github.com/zenhack/python-pgpmime
Author: Ian Denhardt
Author-email: ian@zenhack.net
License: GPLv3+
Platform: UNKNOWN
Classifier: Development Status :: 3 - Alpha
Classifier: Intended Audience :: Developers
Classifier: License :: OSI Approved :: GNU General Public License v3 or later (GPLv3+)
Classifier: Programming Language :: Python :: 2
Classifier: Programming Language :: Python :: 2.7
